hypymedia/__init__.py
hypymedia/html_list.py
hypymedia/main.py
hypymedia-0.1.16.dist-info/LICENSE
hypymedia-0.1.16.dist-info/METADATA
hypymedia-0.1.16.dist-info/WHEEL
hypymedia-0.1.16.dist-info/RECORD
